flask_oidc_sso/__init__.py
flask_oidc_sso/discovery.py
flask_oidc_sso/registration.py
flask_oidc_sso/registration_util.py
flask_oidc_sso-1.4.7.dist-info/LICENSE.txt
flask_oidc_sso-1.4.7.dist-info/METADATA
flask_oidc_sso-1.4.7.dist-info/WHEEL
flask_oidc_sso-1.4.7.dist-info/entry_points.txt
flask_oidc_sso-1.4.7.dist-info/top_level.txt
flask_oidc_sso-1.4.7.dist-info/RECORD
